LICENSE
README.md
setup.py
TwitchChannelPointsMiner/TwitchChannelPointsMiner.py
TwitchChannelPointsMiner/__init__.py
TwitchChannelPointsMiner/constants.py
TwitchChannelPointsMiner/logger.py
TwitchChannelPointsMiner/utils.py
TwitchChannelPointsMiner/classes/AnalyticsServer.py
TwitchChannelPointsMiner/classes/Chat.py
TwitchChannelPointsMiner/classes/Discord.py
TwitchChannelPointsMiner/classes/Exceptions.py
TwitchChannelPointsMiner/classes/Settings.py
TwitchChannelPointsMiner/classes/Telegram.py
TwitchChannelPointsMiner/classes/Twitch.py
TwitchChannelPointsMiner/classes/TwitchLogin.py
TwitchChannelPointsMiner/classes/TwitchWebSocket.py
TwitchChannelPointsMiner/classes/WebSocketsPool.py
TwitchChannelPointsMiner/classes/__init__.py
TwitchChannelPointsMiner/classes/entities/Bet.py
TwitchChannelPointsMiner/classes/entities/Campaign.py
TwitchChannelPointsMiner/classes/entities/Drop.py
TwitchChannelPointsMiner/classes/entities/EventPrediction.py
TwitchChannelPointsMiner/classes/entities/Message.py
TwitchChannelPointsMiner/classes/entities/PubsubTopic.py
TwitchChannelPointsMiner/classes/entities/Raid.py
TwitchChannelPointsMiner/classes/entities/Stream.py
TwitchChannelPointsMiner/classes/entities/Streamer.py
TwitchChannelPointsMiner/classes/entities/__init__.py
Twitch_Channel_Points_Miner_v2.egg-info/PKG-INFO
Twitch_Channel_Points_Miner_v2.egg-info/SOURCES.txt
Twitch_Channel_Points_Miner_v2.egg-info/dependency_links.txt
Twitch_Channel_Points_Miner_v2.egg-info/requires.txt
Twitch_Channel_Points_Miner_v2.egg-info/top_level.txt