Metadata-Version: 2.1
Name: Twitch-Channel-Points-Miner-v2
Version: 2.1.1
Summary: A simple script that will watch a stream for you and earn the channel points.
Home-page: https://github.com/Tkd-Alex/Twitch-Channel-Points-Miner-v2
Author: Tkd-Alex (Alessandro Maggio)
Author-email: alex.tkd.alex@gmail.com
License: GPLv3+
Keywords: python bot streaming script miner twtich channel-points
Platform: UNKNOWN
Classifier: Programming Language :: Python :: 3.6
Classifier: Programming Language :: Python :: 3.7
Classifier: Programming Language :: Python :: 3.8
Classifier: Programming Language :: Python :: 3.9
Classifier: Operating System :: OS Independent
Classifier: Topic :: Utilities
Classifier: Topic :: Software Development :: Libraries :: Python Modules
Classifier: Topic :: Scientific/Engineering
Classifier: Topic :: Software Development :: Version Control :: Git
Classifier: License :: OSI Approved :: GNU General Public License v3 or later (GPLv3+)
Classifier: Natural Language :: English
Requires-Python: >=3.6
License-File: LICENSE
